libPVRTexLib.so
_pypvrtex.cpython-36m-x86_64-linux-gnu.so
texture_tool-0.0.2.dist-info/top_level.txt
texture_tool-0.0.2.dist-info/WHEEL
texture_tool-0.0.2.dist-info/METADATA
texture_tool-0.0.2.dist-info/RECORD
texture_tool/transcode.py
texture_tool/Texture.py
texture_tool/cubemap_from_equirectangular.py
texture_tool/imread.py
texture_tool/_pvrtex_loader.py
texture_tool/coordinate_transform.py
texture_tool/utils.py
texture_tool/downsample2x.py
texture_tool/describe.py
texture_tool/__init__.py
texture_tool/generate_mipmaps.py
