Metadata-Version: 2.1
Name: texture-tool
Version: 0.0.2
Summary: Reading images, PVRTC compression, ETC compression, PVR DDS containers, transcoding, mipmap generation, equirectangular to cubemap. 
Home-page: https://github.com/podgorskiy/texture-tool
Author: Stanislav Pidhorskyi
Author-email: stpidhorskyi@mix.wvu.edu
License: MIT
Keywords: texture_tool
Platform: UNKNOWN
Classifier: Development Status :: 3 - Alpha
Classifier: License :: OSI Approved :: MIT License
Classifier: Programming Language :: Python :: 3.5
Classifier: Programming Language :: Python :: 3.6
Classifier: Programming Language :: Python :: 3.7
Classifier: Programming Language :: Python :: 3.8
Requires-Dist: imageio
Requires-Dist: numpy
Requires-Dist: scipy
